{"Buildings": [{"BuildingArea": "", "BuildingID": "", "BuildingLocation": {"Latitude": "", "Longitude": ""}, "BuildingName": "West Wing Building", "Coordinates": "", "Machines": [{"DeviceID": "Machine1", "DeviceManufacturer": "", "DeviceModel": "", "EnergyMeters": [{"DeviceID": "Energy Meter 1", "DeviceManufacturer": "", "DeviceModel": "", "MeteringService": {"CurrentMeasurement": {"MeasurementTimeInterval": "1s", "MeasurementTimeStamp": {"mapping_type": "database", "connector": "connector_mysql_local01", "mapping": {"dbname": "energymeters", "table": "block_13", "column": "energy"}}, "MeasurementUnit": "KW/h", "Measurementvalue": {"mapping_type": "database", "connector": "connector_mysql_local01", "mapping": {"dbname": "energymeters", "table": "block_13", "column": "tstp"}}}, "ServiceName": ""}}]}, {"DeviceID": "Machine2", "DeviceManufacturer": "", "DeviceModel": "", "EnergyMeters": [{"DeviceID": "Energy Meter 1", "DeviceManufacturer": "", "DeviceModel": "", "MeteringService": {"CurrentMeasurement": {"MeasurementTimeInterval": "1s", "MeasurementTimeStamp": {"mapping_type": "database", "connector": "connector_mysql_local01", "mapping": {"dbname": "energymeters", "table": "block_13", "column": "energy"}}, "MeasurementUnit": "KW/h", "Measurementvalue": {"mapping_type": "database", "connector": "connector_mysql_local01", "mapping": {"dbname": "energymeters", "table": "block_13", "column": "tstp"}}}, "ServiceName": ""}}]}], "Weather": {"AtmosphoricPressure": "", "Cloudage": "", "DayTime": "", "Precipitation": "", "Visibility": "", "WeatherCondition": ""}}]}